sumtyme/__init__.py
sumtyme/sumtyme.py
sumtyme-2.0.3.dist-info/METADATA
sumtyme-2.0.3.dist-info/WHEEL
sumtyme-2.0.3.dist-info/top_level.txt
sumtyme-2.0.3.dist-info/RECORD
