Metadata-Version: 2.1
Name: sumtyme
Version: 2.0.3
Summary: Python Client for Causal Intelligence Layer (CIL) by sumtyme.ai
Home-page: https://docs.sumtyme.ai/
Author: sumteam
Author-email: team@sumtyme.ai
License: UNKNOWN
Platform: UNKNOWN
Classifier: Programming Language :: Python :: 3.12
Classifier: License :: OSI Approved :: MIT License
Classifier: Operating System :: OS Independent
Classifier: Development Status :: 5 - Production/Stable
Classifier: Intended Audience :: Developers
Classifier: Topic :: Scientific/Engineering :: Artificial Intelligence
Classifier: Topic :: Software Development :: Libraries :: Python Modules
Requires-Python: >=3.12
Requires-Dist: pandas (==3.0.0)
Requires-Dist: requests (==2.32.3)
Requires-Dist: numpy (==2.4.1)
Requires-Dist: pyarrow (==23.0.0)
